merf/__init__.py
merf/merf.py
merf/merf_test.py
merf/utils.py
merf/viz.py
merf-1.0.dist-info/LICENSE
merf-1.0.dist-info/METADATA
merf-1.0.dist-info/WHEEL
merf-1.0.dist-info/top_level.txt
merf-1.0.dist-info/RECORD
