Metadata-Version: 2.1
Name: merf
Version: 1.0
Summary: Mixed Effects Random Forest
Home-page: https://github.com/manifoldai/merf
Author: Manifold, Inc.
Author-email: sdey@manifold.ai
License: MIT
Keywords: random forest machine learning mixed effects
Platform: UNKNOWN
Classifier: Development Status :: 3 - Alpha
Classifier: License :: OSI Approved :: MIT License
Classifier: Programming Language :: Python :: 3.6
Classifier: Topic :: Scientific/Engineering :: Artificial Intelligence
Requires-Python: >=3.6
Requires-Dist: pandas (>=1.0)
Requires-Dist: numpy
Requires-Dist: scikit-learn
Requires-Dist: matplotlib (>=3.0)
